{"steps":[{"hasPitch":true,"midiNumber":57,"str":"A4"},{"hasPitch":true,"midiNumber":48,"str":"C4"},{"hasPitch":false,"str":""},{"hasPitch":false,"str":""},{"hasPitch":true,"midiNumber":44,"str":"G#3"},{"hasPitch":false,"str":""},{"hasPitch":true,"midiNumber":58,"str":"A#4"},{"hasPitch":false,"str":""},{"hasPitch":false,"str":""},{"hasPitch":true,"midiNumber":48,"str":"C4"},{"hasPitch":false,"str":""},{"hasPitch":false,"str":""},{"hasPitch":true,"midiNumber":44,"str":"G#3"},{"hasPitch":false,"str":""},{"hasPitch":false,"str":""},{"hasPitch":false,"str":""}],"tempo":140,"stepsPerBeat":2,"title":"New Sequence","composer":"anon","edited":true}